prtg/__init__.py
prtg/api.py
prtg/auth.py
prtg/exception.py
prtg/icon.py
pyprtg_api-0.0.20.dist-info/LICENSE
pyprtg_api-0.0.20.dist-info/METADATA
pyprtg_api-0.0.20.dist-info/WHEEL
pyprtg_api-0.0.20.dist-info/top_level.txt
pyprtg_api-0.0.20.dist-info/RECORD
