Metadata-Version: 2.1
Name: pyprtg-api
Version: 0.0.20
Summary: Client API to communicate with PRTG instance.
Author-email: Jonny Le <jonny.le@computacenter.com>
License: MIT
Project-URL: Repository, https://github.com/CC-Digital-Innovation/pyprtg-api.git
Classifier: Programming Language :: Python :: 3
License-File: LICENSE
Requires-Dist: certifi <2025,>=2024.2.2
Requires-Dist: requests <3,>=2.31.0
Requires-Dist: tenacity <9,>=8.2.2
Requires-Dist: urllib3 <3,>=2.2.1
